mood_suggester/__init__.py
mood_suggester/suggestions.py
mood_suggester-0.1.0.dist-info/LICENSE.txt
mood_suggester-0.1.0.dist-info/METADATA
mood_suggester-0.1.0.dist-info/WHEEL
mood_suggester-0.1.0.dist-info/top_level.txt
mood_suggester-0.1.0.dist-info/RECORD
