Metadata-Version: 2.2
Name: mood_suggester
Version: 0.1.0
Summary: A package to suggest activities based on mood.
Home-page: https://github.com/software-students-spring2025/3-python-package-chugthiskoolaid
Author: Hao Yang
Author-email: hy2640@nyu.edu
Classifier: Programming Language :: Python :: 3
Classifier: License :: OSI Approved :: MIT License
Classifier: Operating System :: OS Independent
Requires-Python: >=3.6
License-File: LICENSE.txt
Dynamic: author
Dynamic: author-email
Dynamic: classifier
Dynamic: description-content-type
Dynamic: home-page
Dynamic: requires-python
Dynamic: summary
